mailing_backend/__init__.py
mailing_backend/apps.py
mailing_backend/backend.py
mailing_backend-1.0.5.dist-info/METADATA
mailing_backend-1.0.5.dist-info/WHEEL
mailing_backend-1.0.5.dist-info/top_level.txt
mailing_backend-1.0.5.dist-info/RECORD
