Metadata-Version: 2.1
Name: mailing_backend
Version: 1.0.5
Summary: Django app for an endpoint mailing.
Author-email: QW_SD_7 <paxomov.2004@list.ru>
Classifier: Programming Language :: Python :: 3
Classifier: Programming Language :: Python :: 3.10
Classifier: Programming Language :: Python :: 3.11
Classifier: Programming Language :: Python :: 3.12
Classifier: Programming Language :: Python :: 3 :: Only
Requires-Python: >=3.11
Requires-Dist: Django >=4.2
Requires-Dist: requests >=2.31
Requires-Dist: djangorestframework >=3.14
